suntime/__init__.py
suntime/suntime.py
dt_suntime-1.0.0.dist-info/LICENSE
dt_suntime-1.0.0.dist-info/METADATA
dt_suntime-1.0.0.dist-info/WHEEL
dt_suntime-1.0.0.dist-info/top_level.txt
dt_suntime-1.0.0.dist-info/RECORD
