Metadata-Version: 2.1
Name: dt-suntime
Version: 1.0.0
Summary: Simple sunset and sunrise time calculation python library
Home-page: https://github.com/DTBird-DTBat/suntime
Author: DTBird&DTBat
License: LGPLv3
License-File: LICENSE
Requires-Dist: python-dateutil
